pycricbuzz/__init__.py
pycricbuzz/cricbuzz.py
pycricbuzz-2.3.dist-info/LICENSE.txt
pycricbuzz-2.3.dist-info/METADATA
pycricbuzz-2.3.dist-info/WHEEL
pycricbuzz-2.3.dist-info/top_level.txt
pycricbuzz-2.3.dist-info/RECORD
